fastapi_mvc/__init__.py
fastapi_mvc/__main__.py
fastapi_mvc/cli/__init__.py
fastapi_mvc/cli/base.py
fastapi_mvc/cli/cli.py
fastapi_mvc/cli/generate.py
fastapi_mvc/cli/new.py
fastapi_mvc/cli/run.py
fastapi_mvc/cli/update.py
fastapi_mvc/constants.py
fastapi_mvc/generators/__init__.py
fastapi_mvc/generators/controller.py
fastapi_mvc/generators/generator.py
fastapi_mvc/generators/loader.py
fastapi_mvc/generators/script.py
fastapi_mvc/py.typed
fastapi_mvc/utils/__init__.py
fastapi_mvc/utils/excepthook.py
fastapi_mvc/utils/generators.py
fastapi_mvc/utils/shell.py
fastapi_mvc-0.28.0.dist-info/LICENSE
fastapi_mvc-0.28.0.dist-info/entry_points.txt
fastapi_mvc-0.28.0.dist-info/WHEEL
fastapi_mvc-0.28.0.dist-info/METADATA
fastapi_mvc-0.28.0.dist-info/RECORD
