Metadata-Version: 2.1
Name: fastapi-mvc
Version: 0.28.0
Summary: Developer productivity tool for making high-quality FastAPI production-ready APIs.
Home-page: https://github.com/fastapi-mvc/fastapi-mvc
License: MIT
Author: Radosław Szamszur
Author-email: github@rsd.sh
Requires-Python: >=3.8,<4.0
Classifier: Development Status :: 3 - Alpha
Classifier: Framework :: FastAPI
Classifier: Intended Audience :: Developers
Classifier: License :: OSI Approved :: MIT License
Classifier: Natural Language :: English
Classifier: Operating System :: OS Independent
Classifier: Programming Language :: Python :: 3
Classifier: Programming Language :: Python :: 3.8
Classifier: Programming Language :: Python :: 3.9
Classifier: Programming Language :: Python :: 3.10
Classifier: Programming Language :: Python :: 3.11
Classifier: Programming Language :: Python :: 3
Classifier: Programming Language :: Python :: 3.10
Classifier: Programming Language :: Python :: 3.11
Classifier: Programming Language :: Python :: 3.8
Classifier: Programming Language :: Python :: 3.9
Classifier: Topic :: Software Development
Classifier: Topic :: Software Development :: Build Tools
Classifier: Topic :: Software Development :: Code Generators
Classifier: Topic :: Software Development :: Libraries
Classifier: Topic :: Software Development :: Libraries :: Python Modules
Requires-Dist: click (>=8.1.3,<8.2.0)
Requires-Dist: copier (==6.2.0)
Project-URL: Documentation, https://fastapi-mvc.netlify.app
Project-URL: Issues, https://github.com/fastapi-mvc/fastapi-mvc/issues
Project-URL: Repository, https://github.com/fastapi-mvc/fastapi-mvc
